{
    "player name": "Kuldeep Yadav",
    "team": "India",
    "player of matches received": 0,
    "match stats": [
        {
            "venue": "Sir Vivian Richards Stadium, North Sound",
            "date": "2017-06-30T00:00:00.000Z",
            "fours": 0,
            "sixes": 0,
            "total runs": 0,
            "wickets": {
                "bowled": 1,
                "run_out": 0,
                "caught": 0
            },
            "wides": 0
        },
        {
            "venue": "Sir Vivian Richards Stadium, North Sound",
            "date": "2017-07-02T00:00:00.000Z",
            "fours": 0,
            "sixes": 0,
            "total runs": 2,
            "wickets": {
                "bowled": 1,
                "run_out": 0,
                "caught": 0
            },
            "wides": 0
        },
        {
            "venue": "Sabina Park, Kingston",
            "date": "2017-07-06T00:00:00.000Z",
            "fours": 0,
            "sixes": 0,
            "total runs": 0,
            "wickets": {
                "bowled": 0,
                "run_out": 0,
                "caught": 1
            },
            "wides": 0
        }
    ]
}